PyBWE/__init__.py
PyBWE/function_BWE.py
PyBWE/function_ar_extrapolation.py
PyBWE/function_burg.py
PyBWE/function_mcov.py
PyPBWE/__init__.py
PyPBWE/function_PBWE.py
PyPBWE/function_polar_burg.py
PyPBWE/function_polar_extrapolation.py
PySSBWE/__init__.py
PySSBWE/function_AIC.py
PySSBWE/function_MDL.py
PySSBWE/function_SSBWE.py
PySSBWE/function_statespace_extrapolation.py
PySSBWE/function_statespace_model.py
PySSBWE/function_statespace_properties.py
PySSBWE/function_two_line_fit.py
PyBWE-2025.2.2.dist-info/LICENSE
PyBWE-2025.2.2.dist-info/METADATA
PyBWE-2025.2.2.dist-info/WHEEL
PyBWE-2025.2.2.dist-info/top_level.txt
PyBWE-2025.2.2.dist-info/RECORD
