Metadata-Version: 2.2
Name: PyBWE
Version: 2025.2.2
Summary: Python tools for Bandwidth Extrapolation (BWE) of radar data
Home-page: https://github.com/NicOudart/PyBWE
Author: Nicolas OUDART
Author-email: nicolas.oudart@latmos.ipsl.fr
Keywords: bwe,radar,resolution,bandwidth,extrapolation,sounder,planetary,science,astronomy,astrophysics,signal processing,spectral
Classifier: Programming Language :: Python :: 3
Classifier: License :: OSI Approved :: MIT License
Classifier: Operating System :: OS Independent
Classifier: Intended Audience :: Science/Research
Classifier: Topic :: Scientific/Engineering :: Astronomy
Requires-Python: >=3.7
License-File: LICENSE
Requires-Dist: numpy
Requires-Dist: matplotlib
Requires-Dist: scipy
Dynamic: author
Dynamic: author-email
Dynamic: classifier
Dynamic: description
Dynamic: description-content-type
Dynamic: home-page
Dynamic: keywords
Dynamic: requires-dist
Dynamic: requires-python
Dynamic: summary
